{
  "spawnWeight": 1,
  "name": "Player",
  "characterTypes": [
    "SurvivorF_Baty",
    "SurvivorF_Eva",
    "SurvivorF_Frida",
    "SurvivorF_Gabi",
    "SurvivorF_Helga",
    "SurvivorF_Irena",
    "SurvivorF_Keiko",
    "SurvivorF_Linda",
    "SurvivorF_Maria",
    "SurvivorF_Naomi"
  ],
  "attachmentSlotItemSets": [
    {
      "slotName": "Headgear",
      "discreteItemSets": [
        {
          "itemType": "WitchHat",
          "spawnWeight": 1,
          "attributes": {
            "healthMin": 1.0,
            "healthMax": 1.0,
            "quantityMin": 1.0,
            "quantityMax": 1.0
          },
          "quickBarSlot": -1
        }
      ]
    },
    {
      "slotName": "Mask",
      "discreteItemSets": [
        {
          "itemType": "CrookedNose",
          "spawnWeight": 1,
          "attributes": {
            "healthMin": 1.0,
            "healthMax": 1.0,
            "quantityMin": 1.0,
            "quantityMax": 1.0
          },
          "quickBarSlot": -1
        }
      ]
    },
    {
      "slotName": "shoulderL",
      "discreteItemSets": [
        {
          "itemType": "VSS",
          "spawnWeight": 1,
          "attributes": {
            "healthMin": 1.0,
            "healthMax": 1.0,
            "quantityMin": 1.0,
            "quantityMax": 1.0
          },
          "quickBarSlot": 1,
          "complexChildrenTypes": [
            {
              "itemType": "KobraOptic",
              "attributes": {
                "healthMin": 1.0,
                "healthMax": 1.0,
                "quantityMin": 1.0,
                "quantityMax": 1.0
              },
              "quickBarSlot": -1,
              "simpleChildrenUseDefaultAttributes": true,
              "simpleChildrenTypes": ["Battery9V"]
            },
            {
              "itemType": "Mag_VAL_20Rnd",
              "attributes": {
                "healthMin": 1.0,
                "healthMax": 1.0,
                "quantityMin": 1.0,
                "quantityMax": 1.0
              },
              "quickBarSlot": -1
            }
          ]
        }
      ]
    },
    {
      "slotName": "shoulderR",
      "discreteItemSets": [
        {
          "itemType": "LongTorch",
          "spawnWeight": 1,
          "attributes": {
            "healthMin": 1.0,
            "healthMax": 1.0,
            "quantityMin": 1.0,
            "quantityMax": 1.0
          },
          "quickBarSlot": 2,
          "complexChildrenTypes": [
            {
              "itemType": "Rag",
              "attributes": {
                "healthMin": 1.0,
                "healthMax": 1.0,
                "quantityMin": 1.0,
                "quantityMax": 1.0
              },
              "quickBarSlot": -1,
              "simpleChildrenUseDefaultAttributes": true,
              "simpleChildrenTypes": [
                "Rag",
                "Rag",
                "Rag",
                "Rag",
                "Rag",
                "Rag",
                "Lard",
                "Lard",
                "Lard"
              ]
            }
          ]
        }
      ]
    },
    {
      "slotName": "Body",
      "discreteItemSets": [
        {
          "itemType": "Raincoat_Black",
          "spawnWeight": 1,
          "attributes": {
            "healthMin": 1.0,
            "healthMax": 1.0,
            "quantityMin": 1.0,
            "quantityMax": 1.0
          },
          "quickBarSlot": -1,
          "simpleChildrenUseDefaultAttributes": false,
          "simpleChildrenTypes": [
            "Grenade_ChemGas",
            "Grenade_ChemGas",
            "Grenade_ChemGas"
          ]
        }
      ]
    },
    {
      "slotName": "Hips",
      "discreteItemSets": [
        {
          "itemType": "MilitaryBelt",
          "spawnWeight": 1,
          "attributes": {
            "healthMin": 1.0,
            "healthMax": 1.0,
            "quantityMin": 1.0,
            "quantityMax": 1.0
          },
          "quickBarSlot": -1,
          "complexChildrenTypes": [
            {
              "itemType": "Canteen",
              "attributes": {
                "healthMin": 1.0,
                "healthMax": 1.0,
                "quantityMin": 1.0,
                "quantityMax": 1.0
              },
              "quickBarSlot": 5
            },
            {
              "itemType": "NylonKnifeSheath",
              "attributes": {
                "healthMin": 1.0,
                "healthMax": 1.0,
                "quantityMin": 1.0,
                "quantityMax": 1.0
              },
              "quickBarSlot": -1,
              "complexChildrenTypes": [
                {
                  "itemType": "FangeKnife",
                  "attributes": {
                    "healthMin": 1.0,
                    "healthMax": 1.0,
                    "quantityMin": 1.0,
                    "quantityMax": 1.0
                  },
                  "quickBarSlot": 4
                }
              ]
            },
            {
              "itemType": "PlateCarrierHolster_Black",
              "attributes": {
                "healthMin": 1.0,
                "healthMax": 1.0,
                "quantityMin": 1.0,
                "quantityMax": 1.0
              },
              "quickBarSlot": -1,
              "complexChildrenTypes": [
                {
                  "itemType": "Glock19",
                  "attributes": {
                    "healthMin": 1.0,
                    "healthMax": 1.0,
                    "quantityMin": 1.0,
                    "quantityMax": 1.0
                  },
                  "quickBarSlot": 3,
                  "simpleChildrenUseDefaultAttributes": true,
                  "simpleChildrenTypes": ["Mag_Glock_15Rnd"]
                }
              ]
            }
          ]
        }
      ]
    },
    {
      "slotName": "Legs",
      "discreteItemSets": [
        {
          "itemType": "CargoPants_Black",
          "spawnWeight": 1,
          "attributes": {
            "healthMin": 1.0,
            "healthMax": 1.0,
            "quantityMin": 1.0,
            "quantityMax": 1.0
          },
          "quickBarSlot": -1,
          "simpleChildrenUseDefaultAttributes": true,
          "simpleChildrenTypes": [
            "PetrolLighter",
            "PunchedCard",
            "TetracyclineAntibiotics",
            "VitaminBottle",
            "BandageDressing",
            "BandageDressing",
            "BandageDressing"
          ]
        }
      ]
    },
    {
      "slotName": "Feet",
      "discreteItemSets": [
        {
          "itemType": "MedievalBoots",
          "spawnWeight": 1,
          "attributes": {
            "healthMin": 1.0,
            "healthMax": 1.0,
            "quantityMin": 1.0,
            "quantityMax": 1.0
          },
          "quickBarSlot": -1
        }
      ]
    },
    {
      "slotName": "Gloves",
      "discreteItemSets": [
        {
          "itemType": "PaddedGloves_Brown",
          "spawnWeight": 1,
          "attributes": {
            "healthMin": 1.0,
            "healthMax": 1.0,
            "quantityMin": 1.0,
            "quantityMax": 1.0
          },
          "quickBarSlot": -1
        },
        {
          "itemType": "PaddedGloves_Beige",
          "spawnWeight": 1,
          "attributes": {
            "healthMin": 1.0,
            "healthMax": 1.0,
            "quantityMin": 1.0,
            "quantityMax": 1.0
          },
          "quickBarSlot": -1
        },
        {
          "itemType": "PaddedGloves_Threat",
          "spawnWeight": 1,
          "attributes": {
            "healthMin": 1.0,
            "healthMax": 1.0,
            "quantityMin": 1.0,
            "quantityMax": 1.0
          },
          "quickBarSlot": -1
        }
      ]
    },
    {
      "slotName": "Vest",
      "discreteItemSets": [
        {
          "itemType": "HighCapacityVest_Black",
          "spawnWeight": 1,
          "attributes": {
            "healthMin": 1.0,
            "healthMax": 1.0,
            "quantityMin": 1.0,
            "quantityMax": 1.0
          },
          "quickBarSlot": -1
        }
      ]
    },
    {
      "slotName": "Back",
      "discreteItemSets": [
        {
          "itemType": "Slingbag_Black",
          "spawnWeight": 1,
          "attributes": {
            "healthMin": 0.8,
            "healthMax": 0.8,
            "quantityMin": 1.0,
            "quantityMax": 1.0
          },
          "quickBarSlot": -1
        }
      ]
    },
    {
      "slotName": "Hands",
      "discreteItemSets": [
        {
          "itemType": "Grenade_ChemGas",
          "spawnWeight": 1,
          "attributes": {
            "healthMin": 1.0,
            "healthMax": 1.0,
            "quantityMin": 1.0,
            "quantityMax": 1.0
          },
          "quickBarSlot": -1
        }
      ]
    }
  ],
  "discreteUnsortedItemSets": [
    {
      "name": "Cargo1",
      "spawnWeight": 1,
      "attributes": {
        "healthMin": 1.0,
        "healthMax": 1.0,
        "quantityMin": 1.0,
        "quantityMax": 1.0
      },
      "complexChildrenTypes": [
        {
          "itemType": "Grenade_ChemGas",
          "attributes": {
            "healthMin": 1.0,
            "healthMax": 1.0,
            "quantityMin": 1.0,
            "quantityMax": 1.0
          },
          "quickBarSlot": -1
        },
        {
          "itemType": "Grenade_ChemGas",
          "attributes": {
            "healthMin": 1.0,
            "healthMax": 1.0,
            "quantityMin": 1.0,
            "quantityMax": 1.0
          },
          "quickBarSlot": -1
        },
        {
          "itemType": "Grenade_ChemGas",
          "attributes": {
            "healthMin": 1.0,
            "healthMax": 1.0,
            "quantityMin": 1.0,
            "quantityMax": 1.0
          },
          "quickBarSlot": -1
        },
        {
          "itemType": "FirstAidKit",
          "attributes": {
            "healthMin": 0.7,
            "healthMax": 0.8,
            "quantityMin": 0.05,
            "quantityMax": 0.1
          },
          "quickBarSlot": -1,
          "simpleChildrenUseDefaultAttributes": false,
          "simpleChildrenTypes": [
            "BandageDressing",
            "TetracyclineAntibiotics",
            "StartKitIV",
            "BloodBagEmpty",
            "BloodTestKit"
          ]
        }
      ],
      "simpleChildrenUseDefaultAttributes": false,
      "simpleChildrenTypes": ["GlassBottle", "GlassBottle"]
    },
    {
      "name": "Cargo2",
      "spawnWeight": 1,
      "attributes": {
        "healthMin": 1.0,
        "healthMax": 1.0,
        "quantityMin": 1.0,
        "quantityMax": 1.0
      },
      "complexChildrenTypes": [
        {
          "itemType": "Grenade_ChemGas",
          "attributes": {
            "healthMin": 1.0,
            "healthMax": 1.0,
            "quantityMin": 1.0,
            "quantityMax": 1.0
          },
          "quickBarSlot": -1
        },
        {
          "itemType": "Grenade_ChemGas",
          "attributes": {
            "healthMin": 1.0,
            "healthMax": 1.0,
            "quantityMin": 1.0,
            "quantityMax": 1.0
          },
          "quickBarSlot": -1
        },
        {
          "itemType": "Grenade_ChemGas",
          "attributes": {
            "healthMin": 1.0,
            "healthMax": 1.0,
            "quantityMin": 1.0,
            "quantityMax": 1.0
          },
          "quickBarSlot": -1
        },
        {
          "itemType": "FirstAidKit",
          "attributes": {
            "healthMin": 0.7,
            "healthMax": 0.8,
            "quantityMin": 0.05,
            "quantityMax": 0.1
          },
          "quickBarSlot": -1,
          "simpleChildrenUseDefaultAttributes": false,
          "simpleChildrenTypes": [
            "BandageDressing",
            "TetracyclineAntibiotics",
            "StartKitIV",
            "BloodBagEmpty",
            "BloodTestKit"
          ]
        }
      ],
      "simpleChildrenUseDefaultAttributes": false,
      "simpleChildrenTypes": ["GlassBottle", "GlassBottle"]
    },
    {
      "name": "Cargo3",
      "spawnWeight": 1,
      "attributes": {
        "healthMin": 1.0,
        "healthMax": 1.0,
        "quantityMin": 1.0,
        "quantityMax": 1.0
      },
      "complexChildrenTypes": [
        {
          "itemType": "Grenade_ChemGas",
          "attributes": {
            "healthMin": 1.0,
            "healthMax": 1.0,
            "quantityMin": 1.0,
            "quantityMax": 1.0
          },
          "quickBarSlot": -1
        },
        {
          "itemType": "Grenade_ChemGas",
          "attributes": {
            "healthMin": 1.0,
            "healthMax": 1.0,
            "quantityMin": 1.0,
            "quantityMax": 1.0
          },
          "quickBarSlot": -1
        },
        {
          "itemType": "Grenade_ChemGas",
          "attributes": {
            "healthMin": 1.0,
            "healthMax": 1.0,
            "quantityMin": 1.0,
            "quantityMax": 1.0
          },
          "quickBarSlot": -1
        },
        {
          "itemType": "FirstAidKit",
          "attributes": {
            "healthMin": 0.7,
            "healthMax": 0.8,
            "quantityMin": 0.05,
            "quantityMax": 0.1
          },
          "quickBarSlot": -1,
          "simpleChildrenUseDefaultAttributes": false,
          "simpleChildrenTypes": [
            "BandageDressing",
            "TetracyclineAntibiotics",
            "StartKitIV",
            "BloodBagEmpty",
            "BloodTestKit"
          ]
        }
      ],
      "simpleChildrenUseDefaultAttributes": false,
      "simpleChildrenTypes": ["GlassBottle", "GlassBottle"]
    }
  ]
}
